mlops/__init__.py
mlops/metrics.py
mlops/processing.py
mlops/queries.py
mlops/training.py
mlops/awsglue/__init__.py
mlops/awsglue/context.py
mlops/awsglue/data_sink.py
mlops/awsglue/data_source.py
mlops/awsglue/devutils.py
mlops/awsglue/dynamicframe.py
mlops/awsglue/functions.py
mlops/awsglue/gluetypes.py
mlops/awsglue/job.py
mlops/awsglue/utils.py
mlops/awsglue/transforms/__init__.py
mlops/awsglue/transforms/apply_mapping.py
mlops/awsglue/transforms/coalesce.py
mlops/awsglue/transforms/collection_transforms.py
mlops/awsglue/transforms/drop_nulls.py
mlops/awsglue/transforms/dynamicframe_filter.py
mlops/awsglue/transforms/dynamicframe_map.py
mlops/awsglue/transforms/errors_as_dynamicframe.py
mlops/awsglue/transforms/field_transforms.py
mlops/awsglue/transforms/relationalize.py
mlops/awsglue/transforms/repartition.py
mlops/awsglue/transforms/resolve_choice.py
mlops/awsglue/transforms/transform.py
mlops/awsglue/transforms/unbox.py
mlops/awsglue/transforms/unnest_frame.py
mlops_cloud-0.1.dist-info/LICENSE
mlops_cloud-0.1.dist-info/METADATA
mlops_cloud-0.1.dist-info/WHEEL
mlops_cloud-0.1.dist-info/top_level.txt
mlops_cloud-0.1.dist-info/RECORD
